joy_config/__init__.py
joy_config/loader.py
joy_config/base_loader/config_loader.py
joy_config/base_loader/dotenv_loader.py
joy_config/base_loader/json_loader.py
joy_config/base_loader/yaml_loader.py
joy_config-0.1.2.dist-info/licenses/LICENSE
joy_config-0.1.2.dist-info/METADATA
joy_config-0.1.2.dist-info/WHEEL
joy_config-0.1.2.dist-info/top_level.txt
joy_config-0.1.2.dist-info/RECORD
