Metadata-Version: 2.4
Name: joy-config
Version: 0.1.2
Summary: Add your description here
Requires-Python: >=3.12
License-File: LICENSE
Requires-Dist: loguru>=0.7.3
Requires-Dist: pyyaml>=6.0.3
Dynamic: license-file
